instaseis/__init__.py
instaseis/finite_elem_mapping.py
instaseis/helpers.py
instaseis/rotations.py
instaseis/sem_derivatives.py
instaseis/source.py
instaseis/spectral_basis.py
instaseis/benchmark/__init__.py
instaseis/benchmark/__main__.py
instaseis/database_interfaces/__init__.py
instaseis/database_interfaces/base_instaseis_db.py
instaseis/database_interfaces/base_netcdf_instaseis_db.py
instaseis/database_interfaces/forward_instaseis_db.py
instaseis/database_interfaces/forward_merged_instaseis_db.py
instaseis/database_interfaces/mesh.py
instaseis/database_interfaces/reciprocal_instaseis_db.py
instaseis/database_interfaces/reciprocal_merged_instaseis_db.py
instaseis/database_interfaces/remote_instaseis_db.py
instaseis/database_interfaces/syngine_instaseis_db.py
instaseis/gui/__init__.py
instaseis/gui/__main__.py
instaseis/gui/instaseis_gui.py
instaseis/gui/qt4mplcanvas.py
instaseis/gui/qt_window.py
instaseis/gui/qt_window.ui
instaseis/gui/scientific_double_spin_box.py
instaseis/gui/data/earth_marble_ng_800.jpg
instaseis/gui/data/enceladus_jpl_800.jpg
instaseis/gui/data/europa_comp_800.jpg
instaseis/gui/data/ganymede_usgs_800.jpg
instaseis/gui/data/grid.png
instaseis/gui/data/mola_texture_shifted_800.jpg
instaseis/gui/data/titan_radar_colored_800.jpg
instaseis/gui/data/venus_magellan_800.jpg
instaseis/scripts/__init__.py
instaseis/scripts/compare_dbs.py
instaseis/scripts/create_srf.py
instaseis/scripts/repack_db.py
instaseis/server/__init__.py
instaseis/server/__main__.py
instaseis/server/app.py
instaseis/server/instaseis_request.py
instaseis/server/util.py
instaseis/server/data/finite_source_schema.json
instaseis/server/routes/__init__.py
instaseis/server/routes/coordinates.py
instaseis/server/routes/events.py
instaseis/server/routes/finite_source.py
instaseis/server/routes/greens.py
instaseis/server/routes/index.py
instaseis/server/routes/info.py
instaseis/server/routes/seismograms.py
instaseis/server/routes/seismograms_raw.py
instaseis-1.5.0.dist-info/licenses/LICENSE.txt
instaseis-1.5.0.dist-info/METADATA
instaseis-1.5.0.dist-info/WHEEL
instaseis-1.5.0.dist-info/top_level.txt
instaseis-1.5.0.dist-info/RECORD
