Metadata-Version: 2.4
Name: instaseis
Version: 1.5.0
Summary: Instaseis - Instant global seismological waveforms
Author: Martin van Driel, Simon Staehler
Author-email: Lion Krischer <lion.krischer@gmail.com>
Project-URL: Homepage, https://instaseis.net
Classifier: Development Status :: 4 - Beta
Classifier: Intended Audience :: Science/Research
Classifier: Programming Language :: Python :: 3
Classifier: Programming Language :: Python :: Implementation :: CPython
Classifier: Operating System :: OS Independent
Classifier: Topic :: Scientific/Engineering
Classifier: Topic :: Scientific/Engineering :: Physics
Requires-Python: >=3.11
License-File: LICENSE.txt
Requires-Dist: h5py
Requires-Dist: numpy
Requires-Dist: obspy>=1.4
Requires-Dist: tornado>=6.0.0
Requires-Dist: requests
Requires-Dist: geographiclib
Requires-Dist: jsonschema>=2.4.0
Requires-Dist: numba
Provides-Extra: gui
Requires-Dist: PySide6; extra == "gui"
Requires-Dist: pyqtgraph; extra == "gui"
Provides-Extra: tests
Requires-Dist: pytest>=8.0; extra == "tests"
Requires-Dist: pytest-xdist>=3.7.0; extra == "tests"
Requires-Dist: click; extra == "tests"
Requires-Dist: netCDF4; extra == "tests"
Requires-Dist: ruff; extra == "tests"
Requires-Dist: responses; extra == "tests"
Dynamic: license-file
